[
  {
    "full_name": "cipherlogs/uhugrid",
    "stargazers_count": 166,
    "open_issues_count": 2,
    "forks_count": 2
  },
  {
    "full_name": "HexHive/malWASH",
    "stargazers_count": 110,
    "open_issues_count": 0,
    "forks_count": 30
  },
  {
    "full_name": "r4j0x00/exploits",
    "stargazers_count": 2458,
    "open_issues_count": 0,
    "forks_count": 712
  },
  {
    "full_name": "morehwachege/libre",
    "stargazers_count": 2,
    "open_issues_count": 0,
    "forks_count": 0
  },
  {
    "full_name": "public-apis/public-apis",
    "stargazers_count": 215467,
    "open_issues_count": 69,
    "forks_count": 24613
  },
  {
    "full_name": "Homebrew/brew",
    "stargazers_count": 33953,
    "open_issues_count": 48,
    "forks_count": 8220
  },
  {
    "full_name": "hoodiehq/hoodie",
    "stargazers_count": 4343,
    "open_issues_count": 68,
    "forks_count": 457
  },
  {
    "full_name": "rust-lang/rust",
    "stargazers_count": 74311,
    "open_issues_count": 9278,
    "forks_count": 10006
  },
  {
    "full_name": "morehwachege/Bookshelf",
    "stargazers_count": 3,
    "open_issues_count": 0,
    "forks_count": 0
  }
]